README.md
setup.py
taurex_cuda/__init__.py
taurex_cuda/mpi.py
taurex_cuda.egg-info/PKG-INFO
taurex_cuda.egg-info/SOURCES.txt
taurex_cuda.egg-info/dependency_links.txt
taurex_cuda.egg-info/entry_points.txt
taurex_cuda.egg-info/requires.txt
taurex_cuda.egg-info/top_level.txt
taurex_cuda/cia/__init__.py
taurex_cuda/cia/cudacia.py
taurex_cuda/contributions/__init__.py
taurex_cuda/contributions/absorption.py
taurex_cuda/contributions/cia.py
taurex_cuda/contributions/cudacontribution.py
taurex_cuda/contributions/flatmie.py
taurex_cuda/contributions/rayleigh.py
taurex_cuda/contributions/simpleclouds.py
taurex_cuda/model/__init__.py
taurex_cuda/model/emission.py
taurex_cuda/model/transmission.py
taurex_cuda/model/transmissiontwo.py
taurex_cuda/opacity/__init__.py
taurex_cuda/opacity/cudacache.py
taurex_cuda/opacity/cudaopacity.py
taurex_cuda/utils/__init__.py
taurex_cuda/utils/emission.py
taurex_cuda/utils/math.py
taurex_cuda/utils/scattering.py